remotescreen/__init__.py
remotescreen/core.py
remotescreen/__metadata__/DISCLIAIMER.md
remotescreen/__metadata__/LICENSE
remotescreen/__metadata__/README.md
remotescreen/__metadata__/__init__.py
remotescreen/__metadata__/requirements.txt
remotescreen-0.0.15.dist-info/METADATA
remotescreen-0.0.15.dist-info/WHEEL
remotescreen-0.0.15.dist-info/top_level.txt
remotescreen-0.0.15.dist-info/RECORD
