Metadata-Version: 2.1
Name: remotescreen
Version: 0.0.15
Summary: View remote screen via HTTP/HTTPS.
Home-page: http://code.foxe6.kozow.com/remotescreen/
Author: f̣ộx̣ệ6
Author-email: foxe6@pm.me
License: AGPL-3.0
Project-URL: Sourcecode, http://code.foxe6.kozow.com/remotescreen.zip
Project-URL: Documentation, http://code.foxe6.kozow.com/remotescreen/docs/
Project-URL: Example, http://code.foxe6.kozow.com/remotescreen/test/
Project-URL: Funding, https://paypal.me/foxe6
Project-URL: Say Thanks!, https://saythanks.io/to/foxe6
Keywords: remote screen share capture
Platform: UNKNOWN
Classifier: Programming Language :: Python :: 3.9
Classifier: Topic :: Utilities
Classifier: Natural Language :: English
Classifier: Intended Audience :: Developers
Classifier: License :: OSI Approved :: GNU Affero General Public License v3
Classifier: Operating System :: MacOS
Classifier: Operating System :: POSIX
Classifier: Operating System :: Microsoft :: Windows :: Windows 10
Classifier: Development Status :: 5 - Production/Stable
Requires-Python: >=3.5
Requires-Dist: encryptedsocket (>=0.0.1)
Requires-Dist: unencryptedsocket (>=0.0.1)
Requires-Dist: pillow (==7.1.1)
Requires-Dist: tornado (==6.0.4)
Requires-Dist: omnitools (>=0.0.1)
